odoo/addons/l10n_de_steuernummer/README.rst
odoo/addons/l10n_de_steuernummer/__init__.py
odoo/addons/l10n_de_steuernummer/__manifest__.py
odoo/addons/l10n_de_steuernummer/i18n/de.po
odoo/addons/l10n_de_steuernummer/i18n/fr.po
odoo/addons/l10n_de_steuernummer/i18n/l10n_de_steuernummer.pot
odoo/addons/l10n_de_steuernummer/models/__init__.py
odoo/addons/l10n_de_steuernummer/models/res_partner.py
odoo/addons/l10n_de_steuernummer/readme/CONTRIBUTORS.rst
odoo/addons/l10n_de_steuernummer/readme/DESCRIPTION.rst
odoo/addons/l10n_de_steuernummer/readme/ROADMAP.rst
odoo/addons/l10n_de_steuernummer/readme/USAGE.rst
odoo/addons/l10n_de_steuernummer/static/description/icon.png
odoo/addons/l10n_de_steuernummer/static/description/index.html
odoo/addons/l10n_de_steuernummer/tests/__init__.py
odoo/addons/l10n_de_steuernummer/tests/test_l10n_de_steuernummer.py
odoo12_addon_l10n_de_steuernummer-12.0.1.0.0.99.dev6.dist-info/METADATA
odoo12_addon_l10n_de_steuernummer-12.0.1.0.0.99.dev6.dist-info/WHEEL
odoo12_addon_l10n_de_steuernummer-12.0.1.0.0.99.dev6.dist-info/top_level.txt
odoo12_addon_l10n_de_steuernummer-12.0.1.0.0.99.dev6.dist-info/RECORD
